tml_jinja2/__init__.py
tml_jinja2/ext.py
tml_jinja2-0.3.1.dist-info/DESCRIPTION.rst
tml_jinja2-0.3.1.dist-info/METADATA
tml_jinja2-0.3.1.dist-info/metadata.json
tml_jinja2-0.3.1.dist-info/RECORD
tml_jinja2-0.3.1.dist-info/top_level.txt
tml_jinja2-0.3.1.dist-info/WHEEL
