Metadata-Version: 2.0
Name: tml-jinja2
Version: 0.3.1
Summary: Jinja2 tml extension for tranlationexchange.com API
Home-page: https://github.com/pypa/sampleproject
Author: Translation Exchange, Inc.
Author-email: r.kamun@gmail.com
License: MIT
Keywords: tml tml-jinja2 translationexchange
Platform: UNKNOWN
Classifier: Development Status :: 3 - Alpha
Classifier: Intended Audience :: Developers
Classifier: Topic :: Software Development :: Build Tools
Classifier: License :: OSI Approved :: MIT License
Classifier: Programming Language :: Python :: 2
Classifier: Programming Language :: Python :: 2.6
Classifier: Programming Language :: Python :: 2.7
Classifier: Programming Language :: Python :: 3
Classifier: Programming Language :: Python :: 3.3
Classifier: Programming Language :: Python :: 3.4
Classifier: Programming Language :: Python :: 3.5
Requires-Dist: tml[pylibmc] (>=0.3.1)
Requires-Dist: Jinja2 (>=2.8)
